LICENSE
MANIFEST.in
README.md
setup.py
avakas/__init__.py
avakas/__main__.py
avakas/avakas.py
avakas/cli.py
avakas/errors.py
avakas/utils.py
avakas/version.py
avakas.egg-info/PKG-INFO
avakas.egg-info/SOURCES.txt
avakas.egg-info/dependency_links.txt
avakas.egg-info/entry_points.txt
avakas.egg-info/requires.txt
avakas.egg-info/top_level.txt
avakas/flavors/__init__.py
avakas/flavors/ansible.py
avakas/flavors/base.py
avakas/flavors/git.py
avakas/flavors/node.py