Metadata-Version: 1.0
Name: avakas
Version: 2.0.7
Summary: Interact with project version metadata
Home-page: https://github.com/otakup0pe/avakas
Author: Jonathan Freedman
Author-email: jonafree@gmail.com
License: MIT
Platform: UNKNOWN
